pull_pull_request/__init__.py
pull_pull_request/__main__.py
pull_pull_request-0.1.0.dist-info/METADATA
pull_pull_request-0.1.0.dist-info/WHEEL
pull_pull_request-0.1.0.dist-info/entry_points.txt
pull_pull_request-0.1.0.dist-info/licenses/LICENSE
pull_pull_request-0.1.0.dist-info/RECORD
